construct-stubs/__init__.pyi
construct-stubs/core.pyi
construct-stubs/debug.pyi
construct-stubs/expr.pyi
construct-stubs/version.pyi
construct-stubs/lib/__init__.pyi
construct-stubs/lib/binary.pyi
construct-stubs/lib/bitstream.pyi
construct-stubs/lib/containers.pyi
construct-stubs/lib/hex.pyi
construct-stubs/lib/py3compat.pyi
construct_typed/__init__.py
construct_typed/dataclass_struct.py
construct_typed/generic_wrapper.py
construct_typed/py.typed
construct_typed/tenum.py
construct_typed/version.py
construct_typing-0.6.2.dist-info/LICENSE
construct_typing-0.6.2.dist-info/METADATA
construct_typing-0.6.2.dist-info/WHEEL
construct_typing-0.6.2.dist-info/top_level.txt
construct_typing-0.6.2.dist-info/RECORD
