Metadata-Version: 2.1
Name: construct-typing
Version: 0.6.2
Summary: Extension for the python package 'construct' that adds typing features
Home-page: https://github.com/timrid/construct-typing
Author: Tim Riddermann
License: MIT
Keywords: construct,kaitai,declarative,data structure,struct,binary,symmetric,parser,builder,parsing,building,pack,unpack,packer,unpacker,bitstring,bytestring,annotation,type hint,typing,typed,bitstruct,PEP 561
Platform: POSIX
Platform: Windows
Classifier: Development Status :: 3 - Alpha
Classifier: License :: OSI Approved :: MIT License
Classifier: Intended Audience :: Developers
Classifier: Topic :: Software Development :: Libraries :: Python Modules
Classifier: Topic :: Software Development :: Build Tools
Classifier: Topic :: Software Development :: Code Generators
Classifier: Programming Language :: Python :: 3
Classifier: Programming Language :: Python :: 3.7
Classifier: Programming Language :: Python :: 3.8
Classifier: Programming Language :: Python :: 3.9
Classifier: Programming Language :: Python :: 3.10
Classifier: Programming Language :: Python :: 3.11
Classifier: Programming Language :: Python :: Implementation :: CPython
Classifier: Typing :: Typed
Requires-Python: >=3.7
License-File: LICENSE
